MANIFEST.in
README.md
setup.py
examples/all_pairs.py
examples/clustering.py
libripoff.egg-info/PKG-INFO
libripoff.egg-info/SOURCES.txt
libripoff.egg-info/dependency_links.txt
libripoff.egg-info/requires.txt
libripoff.egg-info/top_level.txt
ripoff/__init__.py
ripoff/all_pairs.py
ripoff/clustering.py
ripoff/distances.py
tests/__init__.py
tests/all_pairs.py