Metadata-Version: 1.1
Name: libripoff
Version: 0.2
Summary: simple library to detect plagiarism in source code
Home-page: https://github.com/gravitino/libripoff
Author: Christian Hundt, Moritz Schlarb
Author-email: hundt.christian@gmail.com, mail@moritz-schlarb.de
License: BSD
Platform: UNKNOWN
Classifier: Development Status :: 4 - Beta
Classifier: Topic :: Education
Classifier: Topic :: Scientific/Engineering :: Information Analysis
Classifier: Topic :: Software Development :: Libraries
Classifier: License :: OSI Approved :: BSD License
